gutefrage/__init__.py
gutefrage-0.6.1.dist-info/METADATA
gutefrage-0.6.1.dist-info/WHEEL
gutefrage-0.6.1.dist-info/top_level.txt
gutefrage-0.6.1.dist-info/RECORD
