Metadata-Version: 2.1
Name: gutefrage
Version: 0.6.1
Summary: Unofficial GuteFrage api. Check https://github.com/DAMcraft/gutefrage/wiki on how to use it
Home-page: https://github.com/DAMcraft/gutefrage
Author: DAMcraft
Author-email: 
License: MIT
Platform: UNKNOWN
Requires-Dist: beautifulsoup4 (>=4.9)
Requires-Dist: requests (>=2.22)
